  5           0 BUILD_LIST               0
              2 STORE_FAST               1 (enc)

  6           4 LOAD_FAST                0 (flag)
              6 GET_ITER
        >>    8 FOR_ITER                17 (to 44)
             10 STORE_FAST               2 (i)

  7          12 LOAD_FAST                1 (enc)
             14 LOAD_METHOD              0 (append)
             16 LOAD_GLOBAL              1 (chr)
             18 LOAD_GLOBAL              2 (ord)
             20 LOAD_FAST                2 (i)
             22 CALL_FUNCTION            1
             24 LOAD_CONST               1 (69)
             26 BINARY_XOR
             28 LOAD_CONST               2 (5000)
             30 BINARY_ADD
             32 CALL_FUNCTION            1
             34 LOAD_METHOD              3 (encode)
             36 CALL_METHOD              0
             38 CALL_METHOD              1
             40 POP_TOP
             42 JUMP_ABSOLUTE            4 (to 8)

  8     >>   44 LOAD_CONST               3 (b'')
             46 LOAD_METHOD              4 (join)
             48 LOAD_FAST                1 (enc)
             50 CALL_METHOD              1
             52 LOAD_METHOD              5 (decode)
             54 CALL_METHOD              0
             56 RETURN_VALUE
